MANIFEST.in
README.rst
pyformat.py
setup.py
test_pyformat.py
pyformat.egg-info/PKG-INFO
pyformat.egg-info/SOURCES.txt
pyformat.egg-info/dependency_links.txt
pyformat.egg-info/entry_points.txt
pyformat.egg-info/not-zip-safe
pyformat.egg-info/requires.txt
pyformat.egg-info/top_level.txt