Metadata-Version: 1.1
Name: pyformat
Version: 0.5.1
Summary: Formats Python code to follow a consistent style.
Home-page: https://github.com/myint/pyformat
Author: Steven Myint
Author-email: UNKNOWN
License: Expat License
Keywords: beautify,code,format,formatter,reformat,style
Platform: UNKNOWN
Classifier: Intended Audience :: Developers
Classifier: Environment :: Console
Classifier: License :: OSI Approved :: MIT License
Classifier: Programming Language :: Python :: 2.7
Classifier: Programming Language :: Python :: 3
Classifier: Programming Language :: Python :: 3.2
Classifier: Programming Language :: Python :: 3.3
Classifier: Topic :: Software Development :: Libraries :: Python Modules
